xpatch/__main__.py
xpatch/cliskel.py
xpatch-1.2.0.dist-info/licenses/LICENSE
xpatch-1.2.0.dist-info/METADATA
xpatch-1.2.0.dist-info/WHEEL
xpatch-1.2.0.dist-info/entry_points.txt
xpatch-1.2.0.dist-info/top_level.txt
xpatch-1.2.0.dist-info/RECORD
