Metadata-Version: 2.4
Name: xpatch
Version: 1.2.0
Summary: XML-based binary patching tool with verification support
Author: Biojet1
License:                     GNU GENERAL PUBLIC LICENSE
Project-URL: Homepage, https://github.com/biojet1/xpatch
Project-URL: Documentation, https://github.com/biojet1/xpatch#readme
Project-URL: BugTracker, https://github.com/biojet1/xpatch/issues
Project-URL: Changelog, https://github.com/biojet1/xpatch/releases
Keywords: patch,binary,xml,md5,verification
Classifier: Development Status :: 4 - Beta
Classifier: Intended Audience :: Developers
Classifier: Intended Audience :: System Administrators
Classifier: License :: OSI Approved :: MIT License
Classifier: Operating System :: OS Independent
Classifier: Topic :: Software Development :: Build Tools
Classifier: Topic :: System :: Systems Administration
Classifier: Topic :: Utilities
Requires-Python: >=3.7
License-File: LICENSE
Provides-Extra: dev
Requires-Dist: black>=23.0; extra == "dev"
Requires-Dist: flake8>=6.0; extra == "dev"
Requires-Dist: mypy>=1.0; extra == "dev"
Requires-Dist: pytest>=7.0; extra == "dev"
Provides-Extra: test
Requires-Dist: pytest>=7.0; extra == "test"
Requires-Dist: pytest-cov>=4.0; extra == "test"
Dynamic: license-file
